[
	{
		"name": "DBLP",
		"url": "http://www.informatik.uni-trier.de/~ley/db/indices/a-tree/m/Mu=ntilde=oz:Emir.html"
	},
	{
		"name": "GoogleScholar",
		"url": "http://scholar.google.com/citations?user=ofdUXHIAAAAJ"
	},
	{
		"name": "ResearchGate",
		"url": "https://www.researchgate.net/profile/Emir_Munoz/"
	},
	{
		"name": "ORCID",
		"url": "http://orcid.org/0000-0002-0089-8135"
	},
	{
		"name": "Bibsonomy",
		"url": "http://www.bibsonomy.org/user/emunoz"
	},
        {
               "name": "SemanticScholar",
               "url": "https://www.semanticscholar.org/author/Emir-Mu%C3%B1oz/2441383"
        },
        {
               "name": "MicrosoftAcademic",
               "url": "https://academic.microsoft.com/#/detail/2165782363"
        }
]
